staticclass.py
staticclass-0.0.1.dist-info/LICENCE
staticclass-0.0.1.dist-info/METADATA
staticclass-0.0.1.dist-info/WHEEL
staticclass-0.0.1.dist-info/top_level.txt
staticclass-0.0.1.dist-info/RECORD
