Metadata-Version: 2.1
Name: staticclass
Version: 0.0.1
Summary: staticclass
Author-email: classno <classno@gmail.com>
Classifier: Programming Language :: Python :: 3
Classifier: License :: OSI Approved :: MIT License
Classifier: Operating System :: OS Independent
Requires-Python: >=3.7
License-File: LICENCE
